listele/__init__.py
listele/listele.py
listele-1.0.1.dist-info/licenses/LICENSE
listele-1.0.1.dist-info/METADATA
listele-1.0.1.dist-info/WHEEL
listele-1.0.1.dist-info/top_level.txt
listele-1.0.1.dist-info/RECORD
