Metadata-Version: 2.4
Name: listele
Version: 1.0.1
Summary: Just a printing listed version function.
Author: Esat Saygın
License-Expression: MIT
Classifier: Programming Language :: Python :: 3
Classifier: Operating System :: OS Independent
Requires-Python: >=3.9
License-File: LICENSE
Dynamic: license-file
